client_setup.py
packets/__init__.py
packets/client.py
packets/client/__init__.py
packets/client/add_contact.py
packets/client/database.py
packets/client/del_contact.py
packets/client/main_window.py
packets/client/main_window_conv.py
packets/client/start_dialog.py
packets/client/transport.py
packets/common/__init__.py
packets/common/decos.py
packets/common/descriptors.py
packets/common/errors.py
packets/common/host_ping.py
packets/common/metaclass.py
packets/common/utils.py
packets/common/variables.py
packets/logs/__init__.py
packets/logs/config_client_log.py
packets/logs/config_server_log.py
packets/unit_tests/__init__.py
packets/unit_tests/decos.py
packets/unit_tests/test_client.py
packets/unit_tests/test_utils.py
ship_messenger_client.egg-info/PKG-INFO
ship_messenger_client.egg-info/SOURCES.txt
ship_messenger_client.egg-info/dependency_links.txt
ship_messenger_client.egg-info/requires.txt
ship_messenger_client.egg-info/top_level.txt